{
  "symbols": {
    "sparkles.core_cli.args.cliOption": "/api/symbols/sparkles.core_cli.args.clioption",
    "sparkles.core_cli.args.CliOption": "/api/symbols/sparkles.core_cli.args.clioption--struct",
    "sparkles.core_cli.args.CliOption.aliases": "/api/symbols/sparkles.core_cli.args.clioption.aliases",
    "sparkles.core_cli.args.cliOption.cliOption": "/api/symbols/sparkles.core_cli.args.clioption.clioption",
    "sparkles.core_cli.args.CliOption.description": "/api/symbols/sparkles.core_cli.args.clioption.description",
    "sparkles.core_cli.args.CliParamsStructToDescription": "/api/symbols/sparkles.core_cli.args.cliparamsstructtodescription",
    "sparkles.core_cli.args.CliParamsStructToDescription.CliParamsStructToDescription": "/api/symbols/sparkles.core_cli.args.cliparamsstructtodescription.cliparamsstructtodescription",
    "sparkles.core_cli.args.getOption": "/api/symbols/sparkles.core_cli.args.getoption",
    "sparkles.core_cli.args.getOption.getOption": "/api/symbols/sparkles.core_cli.args.getoption.getoption",
    "sparkles.core_cli.args.importSections": "/api/symbols/sparkles.core_cli.args.importsections",
    "sparkles.core_cli.args.importSections.importSections": "/api/symbols/sparkles.core_cli.args.importsections.importsections",
    "sparkles.core_cli.args.parseCliArgs": "/api/symbols/sparkles.core_cli.args.parsecliargs",
    "sparkles.core_cli.args.parseCliArgs.parseCliArgs": "/api/symbols/sparkles.core_cli.args.parsecliargs.parsecliargs",
    "sparkles.core_cli.args.sparkles.core_cli.help_formatting": "/api/symbols/sparkles.core_cli.args.sparkles.core_cli.help_formatting",
    "sparkles.core_cli.args.tryImport": "/api/symbols/sparkles.core_cli.args.tryimport",
    "sparkles.core_cli.args.tryImport.tryImport": "/api/symbols/sparkles.core_cli.args.tryimport.tryimport",
    "sparkles.core_cli.help_formatting.formatOption": "/api/symbols/sparkles.core_cli.help_formatting.formatoption",
    "sparkles.core_cli.help_formatting.formatProgramManual": "/api/symbols/sparkles.core_cli.help_formatting.formatprogrammanual",
    "sparkles.core_cli.help_formatting.formatSection": "/api/symbols/sparkles.core_cli.help_formatting.formatsection",
    "sparkles.core_cli.help_formatting.formatSynopsis": "/api/symbols/sparkles.core_cli.help_formatting.formatsynopsis",
    "sparkles.core_cli.help_formatting.HelpInfo": "/api/symbols/sparkles.core_cli.help_formatting.helpinfo",
    "sparkles.core_cli.help_formatting.HelpInfo.programName": "/api/symbols/sparkles.core_cli.help_formatting.helpinfo.programname",
    "sparkles.core_cli.help_formatting.HelpInfo.sections": "/api/symbols/sparkles.core_cli.help_formatting.helpinfo.sections",
    "sparkles.core_cli.help_formatting.HelpInfo.shortDescription": "/api/symbols/sparkles.core_cli.help_formatting.helpinfo.shortdescription",
    "sparkles.core_cli.help_formatting.optional": "/api/symbols/sparkles.core_cli.help_formatting.optional",
    "sparkles.core_cli.help_formatting.SectionName": "/api/symbols/sparkles.core_cli.help_formatting.sectionname",
    "sparkles.core_cli.help_formatting.Sections": "/api/symbols/sparkles.core_cli.help_formatting.sections",
    "sparkles.core_cli.help_formatting.SectionText": "/api/symbols/sparkles.core_cli.help_formatting.sectiontext",
    "sparkles.core_cli.help_formatting.wrap2": "/api/symbols/sparkles.core_cli.help_formatting.wrap2",
    "sparkles.core_cli.help_formatting.wrap2.wrap2": "/api/symbols/sparkles.core_cli.help_formatting.wrap2.wrap2",
    "sparkles.core_cli.json.fromJSON": "/api/symbols/sparkles.core_cli.json.fromjson",
    "sparkles.core_cli.json.fromJSON.fromJSON": "/api/symbols/sparkles.core_cli.json.fromjson.fromjson",
    "sparkles.core_cli.json.readJsonFile": "/api/symbols/sparkles.core_cli.json.readjsonfile",
    "sparkles.core_cli.json.readJsonFile.readJsonFile": "/api/symbols/sparkles.core_cli.json.readjsonfile.readjsonfile",
    "sparkles.core_cli.json.toJSON": "/api/symbols/sparkles.core_cli.json.tojson",
    "sparkles.core_cli.json.toJSON.toJSON": "/api/symbols/sparkles.core_cli.json.tojson.tojson",
    "sparkles.core_cli.json.tryDeserializeJson": "/api/symbols/sparkles.core_cli.json.trydeserializejson",
    "sparkles.core_cli.json.tryDeserializeJson.tryDeserializeJson": "/api/symbols/sparkles.core_cli.json.trydeserializejson.trydeserializejson",
    "sparkles.core_cli.json.tryGet": "/api/symbols/sparkles.core_cli.json.tryget",
    "sparkles.core_cli.json.tryGet.tryGet": "/api/symbols/sparkles.core_cli.json.tryget.tryget",
    "sparkles.core_cli.json.writeJsonFile": "/api/symbols/sparkles.core_cli.json.writejsonfile",
    "sparkles.core_cli.json.writeJsonFile.writeJsonFile": "/api/symbols/sparkles.core_cli.json.writejsonfile.writejsonfile",
    "sparkles.core_cli.lifetime.recycledErrorInstance": "/api/symbols/sparkles.core_cli.lifetime.recyclederrorinstance",
    "sparkles.core_cli.lifetime.recycledErrorInstance.recycledErrorInstance": "/api/symbols/sparkles.core_cli.lifetime.recyclederrorinstance.recyclederrorinstance",
    "sparkles.core_cli.lifetime.recycledInstance": "/api/symbols/sparkles.core_cli.lifetime.recycledinstance",
    "sparkles.core_cli.lifetime.recycledInstance.recycledInstance": "/api/symbols/sparkles.core_cli.lifetime.recycledinstance.recycledinstance",
    "sparkles.core_cli.prettyprint.prettyPrint": "/api/symbols/sparkles.core_cli.prettyprint.prettyprint",
    "sparkles.core_cli.prettyprint.prettyPrint.prettyPrint": "/api/symbols/sparkles.core_cli.prettyprint.prettyprint.prettyprint",
    "sparkles.core_cli.prettyprint.PrettyPrintOptions": "/api/symbols/sparkles.core_cli.prettyprint.prettyprintoptions",
    "sparkles.core_cli.prettyprint.PrettyPrintOptions.PrettyPrintOptions": "/api/symbols/sparkles.core_cli.prettyprint.prettyprintoptions.prettyprintoptions",
    "sparkles.core_cli.prettyprint.PrettyPrintOptions.PrettyPrintOptions.indentStep": "/api/symbols/sparkles.core_cli.prettyprint.prettyprintoptions.prettyprintoptions.indentstep",
    "sparkles.core_cli.prettyprint.PrettyPrintOptions.PrettyPrintOptions.maxDepth": "/api/symbols/sparkles.core_cli.prettyprint.prettyprintoptions.prettyprintoptions.maxdepth",
    "sparkles.core_cli.prettyprint.PrettyPrintOptions.PrettyPrintOptions.maxItems": "/api/symbols/sparkles.core_cli.prettyprint.prettyprintoptions.prettyprintoptions.maxitems",
    "sparkles.core_cli.prettyprint.PrettyPrintOptions.PrettyPrintOptions.softMaxWidth": "/api/symbols/sparkles.core_cli.prettyprint.prettyprintoptions.prettyprintoptions.softmaxwidth",
    "sparkles.core_cli.prettyprint.PrettyPrintOptions.PrettyPrintOptions.sourceUriHook": "/api/symbols/sparkles.core_cli.prettyprint.prettyprintoptions.prettyprintoptions.sourceurihook",
    "sparkles.core_cli.prettyprint.PrettyPrintOptions.PrettyPrintOptions.useColors": "/api/symbols/sparkles.core_cli.prettyprint.prettyprintoptions.prettyprintoptions.usecolors",
    "sparkles.core_cli.prettyprint.PrettyPrintOptions.PrettyPrintOptions.useOscLinks": "/api/symbols/sparkles.core_cli.prettyprint.prettyprintoptions.prettyprintoptions.useosclinks",
    "sparkles.core_cli.process_utils.enforceExitStatus": "/api/symbols/sparkles.core_cli.process_utils.enforceexitstatus",
    "sparkles.core_cli.process_utils.executeShell": "/api/symbols/sparkles.core_cli.process_utils.executeshell",
    "sparkles.core_cli.smallbuffer.SmallBuffer": "/api/symbols/sparkles.core_cli.smallbuffer.smallbuffer",
    "sparkles.core_cli.smallbuffer.SmallBuffer.SmallBuffer": "/api/symbols/sparkles.core_cli.smallbuffer.smallbuffer.smallbuffer",
    "sparkles.core_cli.smallbuffer.SmallBuffer.SmallBuffer._capacity": "/api/symbols/sparkles.core_cli.smallbuffer.smallbuffer.smallbuffer._capacity",
    "sparkles.core_cli.smallbuffer.SmallBuffer.SmallBuffer._data": "/api/symbols/sparkles.core_cli.smallbuffer.smallbuffer.smallbuffer._data",
    "sparkles.core_cli.smallbuffer.SmallBuffer.SmallBuffer._length": "/api/symbols/sparkles.core_cli.smallbuffer.smallbuffer.smallbuffer._length",
    "sparkles.core_cli.smallbuffer.SmallBuffer.SmallBuffer._smallBuffer": "/api/symbols/sparkles.core_cli.smallbuffer.smallbuffer.smallbuffer._smallbuffer",
    "sparkles.core_cli.smallbuffer.SmallBuffer.SmallBuffer.~this": "/api/symbols/sparkles.core_cli.smallbuffer.smallbuffer.smallbuffer.-this",
    "sparkles.core_cli.smallbuffer.SmallBuffer.SmallBuffer.back": "/api/symbols/sparkles.core_cli.smallbuffer.smallbuffer.smallbuffer.back",
    "sparkles.core_cli.smallbuffer.SmallBuffer.SmallBuffer.capacity": "/api/symbols/sparkles.core_cli.smallbuffer.smallbuffer.smallbuffer.capacity",
    "sparkles.core_cli.smallbuffer.SmallBuffer.SmallBuffer.clear": "/api/symbols/sparkles.core_cli.smallbuffer.smallbuffer.smallbuffer.clear",
    "sparkles.core_cli.smallbuffer.SmallBuffer.SmallBuffer.data": "/api/symbols/sparkles.core_cli.smallbuffer.smallbuffer.smallbuffer.data",
    "sparkles.core_cli.smallbuffer.SmallBuffer.SmallBuffer.empty": "/api/symbols/sparkles.core_cli.smallbuffer.smallbuffer.smallbuffer.empty",
    "sparkles.core_cli.smallbuffer.SmallBuffer.SmallBuffer.ensureCapacity": "/api/symbols/sparkles.core_cli.smallbuffer.smallbuffer.smallbuffer.ensurecapacity",
    "sparkles.core_cli.smallbuffer.SmallBuffer.SmallBuffer.front": "/api/symbols/sparkles.core_cli.smallbuffer.smallbuffer.smallbuffer.front",
    "sparkles.core_cli.smallbuffer.SmallBuffer.SmallBuffer.length": "/api/symbols/sparkles.core_cli.smallbuffer.smallbuffer.smallbuffer.length",
    "sparkles.core_cli.smallbuffer.SmallBuffer.SmallBuffer.onHeap": "/api/symbols/sparkles.core_cli.smallbuffer.smallbuffer.smallbuffer.onheap",
    "sparkles.core_cli.smallbuffer.SmallBuffer.SmallBuffer.opDollar": "/api/symbols/sparkles.core_cli.smallbuffer.smallbuffer.smallbuffer.opdollar",
    "sparkles.core_cli.smallbuffer.SmallBuffer.SmallBuffer.opIndex": "/api/symbols/sparkles.core_cli.smallbuffer.smallbuffer.smallbuffer.opindex",
    "sparkles.core_cli.smallbuffer.SmallBuffer.SmallBuffer.opOpAssign": "/api/symbols/sparkles.core_cli.smallbuffer.smallbuffer.smallbuffer.opopassign",
    "sparkles.core_cli.smallbuffer.SmallBuffer.SmallBuffer.opOpAssign.opOpAssign": "/api/symbols/sparkles.core_cli.smallbuffer.smallbuffer.smallbuffer.opopassign.opopassign",
    "sparkles.core_cli.smallbuffer.SmallBuffer.SmallBuffer.opSlice": "/api/symbols/sparkles.core_cli.smallbuffer.smallbuffer.smallbuffer.opslice",
    "sparkles.core_cli.smallbuffer.SmallBuffer.SmallBuffer.popBack": "/api/symbols/sparkles.core_cli.smallbuffer.smallbuffer.smallbuffer.popback",
    "sparkles.core_cli.smallbuffer.SmallBuffer.SmallBuffer.put": "/api/symbols/sparkles.core_cli.smallbuffer.smallbuffer.smallbuffer.put",
    "sparkles.core_cli.smallbuffer.SmallBuffer.SmallBuffer.put.put": "/api/symbols/sparkles.core_cli.smallbuffer.smallbuffer.smallbuffer.put.put",
    "sparkles.core_cli.smallbuffer.SmallBuffer.SmallBuffer.reallocate": "/api/symbols/sparkles.core_cli.smallbuffer.smallbuffer.smallbuffer.reallocate",
    "sparkles.core_cli.smallbuffer.SmallBuffer.SmallBuffer.reserve": "/api/symbols/sparkles.core_cli.smallbuffer.smallbuffer.smallbuffer.reserve",
    "sparkles.core_cli.source_uri.EditorDetectHook": "/api/symbols/sparkles.core_cli.source_uri.editordetecthook",
    "sparkles.core_cli.source_uri.EditorDetectHook.writeSourceUri": "/api/symbols/sparkles.core_cli.source_uri.editordetecthook.writesourceuri",
    "sparkles.core_cli.source_uri.EditorDetectHook.writeSourceUri.writeSourceUri": "/api/symbols/sparkles.core_cli.source_uri.editordetecthook.writesourceuri.writesourceuri",
    "sparkles.core_cli.source_uri.EditorScheme": "/api/symbols/sparkles.core_cli.source_uri.editorscheme",
    "sparkles.core_cli.source_uri.EditorScheme.aliases": "/api/symbols/sparkles.core_cli.source_uri.editorscheme.aliases",
    "sparkles.core_cli.source_uri.EditorScheme.name": "/api/symbols/sparkles.core_cli.source_uri.editorscheme.name",
    "sparkles.core_cli.source_uri.EditorScheme.uriFun": "/api/symbols/sparkles.core_cli.source_uri.editorscheme.urifun",
    "sparkles.core_cli.source_uri.editorSchemes": "/api/symbols/sparkles.core_cli.source_uri.editorschemes",
    "sparkles.core_cli.source_uri.FileUriHook": "/api/symbols/sparkles.core_cli.source_uri.fileurihook",
    "sparkles.core_cli.source_uri.FileUriHook.writeSourceUri": "/api/symbols/sparkles.core_cli.source_uri.fileurihook.writesourceuri",
    "sparkles.core_cli.source_uri.FileUriHook.writeSourceUri.writeSourceUri": "/api/symbols/sparkles.core_cli.source_uri.fileurihook.writesourceuri.writesourceuri",
    "sparkles.core_cli.source_uri.hasWriteSourceUri": "/api/symbols/sparkles.core_cli.source_uri.haswritesourceuri",
    "sparkles.core_cli.source_uri.hasWriteSourceUri.hasWriteSourceUri": "/api/symbols/sparkles.core_cli.source_uri.haswritesourceuri.haswritesourceuri",
    "sparkles.core_cli.source_uri.resolveSourcePath": "/api/symbols/sparkles.core_cli.source_uri.resolvesourcepath",
    "sparkles.core_cli.source_uri.SchemeHook": "/api/symbols/sparkles.core_cli.source_uri.schemehook",
    "sparkles.core_cli.source_uri.SchemeHook.SchemeHook": "/api/symbols/sparkles.core_cli.source_uri.schemehook.schemehook",
    "sparkles.core_cli.source_uri.SchemeHook.SchemeHook.writeSourceUri": "/api/symbols/sparkles.core_cli.source_uri.schemehook.schemehook.writesourceuri",
    "sparkles.core_cli.source_uri.SchemeHook.SchemeHook.writeSourceUri.writeSourceUri": "/api/symbols/sparkles.core_cli.source_uri.schemehook.schemehook.writesourceuri.writesourceuri",
    "sparkles.core_cli.string.appendUrlPath": "/api/symbols/sparkles.core_cli.string.appendurlpath",
    "sparkles.core_cli.string.camelCaseToCapitalCase": "/api/symbols/sparkles.core_cli.string.camelcasetocapitalcase",
    "sparkles.core_cli.string.enumFromString": "/api/symbols/sparkles.core_cli.string.enumfromstring",
    "sparkles.core_cli.string.enumFromString.enumFromString": "/api/symbols/sparkles.core_cli.string.enumfromstring.enumfromstring",
    "sparkles.core_cli.string.enumToString": "/api/symbols/sparkles.core_cli.string.enumtostring",
    "sparkles.core_cli.string.enumToString.enumToString": "/api/symbols/sparkles.core_cli.string.enumtostring.enumtostring",
    "sparkles.core_cli.string.getMaxEnumMemberNameLength": "/api/symbols/sparkles.core_cli.string.getmaxenummembernamelength",
    "sparkles.core_cli.string.getMaxEnumMemberNameLength.getMaxEnumMemberNameLength": "/api/symbols/sparkles.core_cli.string.getmaxenummembernamelength.getmaxenummembernamelength",
    "sparkles.core_cli.string.kebabCaseToCamelCase": "/api/symbols/sparkles.core_cli.string.kebabcasetocamelcase",
    "sparkles.core_cli.string.lowerCaseFirst": "/api/symbols/sparkles.core_cli.string.lowercasefirst",
    "sparkles.core_cli.string.MaxWidth": "/api/symbols/sparkles.core_cli.string.maxwidth",
    "sparkles.core_cli.string.MaxWidth.value": "/api/symbols/sparkles.core_cli.string.maxwidth.value",
    "sparkles.core_cli.string.StringRepresentation": "/api/symbols/sparkles.core_cli.string.stringrepresentation",
    "sparkles.core_cli.string.StringRepresentation.repr": "/api/symbols/sparkles.core_cli.string.stringrepresentation.repr",
    "sparkles.core_cli.string.writeRecordAsTable": "/api/symbols/sparkles.core_cli.string.writerecordastable",
    "sparkles.core_cli.string.writeRecordAsTable.writeRecordAsTable": "/api/symbols/sparkles.core_cli.string.writerecordastable.writerecordastable",
    "sparkles.core_cli.styled_template.styled": "/api/symbols/sparkles.core_cli.styled_template.styled",
    "sparkles.core_cli.styled_template.styled.styled": "/api/symbols/sparkles.core_cli.styled_template.styled.styled",
    "sparkles.core_cli.styled_template.styledText": "/api/symbols/sparkles.core_cli.styled_template.styledtext",
    "sparkles.core_cli.styled_template.StyledText": "/api/symbols/sparkles.core_cli.styled_template.styledtext--template",
    "sparkles.core_cli.styled_template.styledText.styledText": "/api/symbols/sparkles.core_cli.styled_template.styledtext.styledtext",
    "sparkles.core_cli.styled_template.StyledText.StyledText": "/api/symbols/sparkles.core_cli.styled_template.styledtext.styledtext--struct",
    "sparkles.core_cli.styled_template.StyledText.StyledText.args": "/api/symbols/sparkles.core_cli.styled_template.styledtext.styledtext.args",
    "sparkles.core_cli.styled_template.StyledText.StyledText.toString": "/api/symbols/sparkles.core_cli.styled_template.styledtext.styledtext.tostring",
    "sparkles.core_cli.styled_template.styledWrite": "/api/symbols/sparkles.core_cli.styled_template.styledwrite",
    "sparkles.core_cli.styled_template.styledWrite.styledWrite": "/api/symbols/sparkles.core_cli.styled_template.styledwrite.styledwrite",
    "sparkles.core_cli.styled_template.styledWriteErr": "/api/symbols/sparkles.core_cli.styled_template.styledwriteerr",
    "sparkles.core_cli.styled_template.styledWriteErr.styledWriteErr": "/api/symbols/sparkles.core_cli.styled_template.styledwriteerr.styledwriteerr",
    "sparkles.core_cli.styled_template.styledWriteln": "/api/symbols/sparkles.core_cli.styled_template.styledwriteln",
    "sparkles.core_cli.styled_template.styledWriteln.styledWriteln": "/api/symbols/sparkles.core_cli.styled_template.styledwriteln.styledwriteln",
    "sparkles.core_cli.styled_template.styledWritelnErr": "/api/symbols/sparkles.core_cli.styled_template.styledwritelnerr",
    "sparkles.core_cli.styled_template.styledWritelnErr.styledWritelnErr": "/api/symbols/sparkles.core_cli.styled_template.styledwritelnerr.styledwritelnerr",
    "sparkles.core_cli.styled_template.styleFromName": "/api/symbols/sparkles.core_cli.styled_template.stylefromname",
    "sparkles.core_cli.styled_template.writeStyled": "/api/symbols/sparkles.core_cli.styled_template.writestyled",
    "sparkles.core_cli.styled_template.writeStyled.writeStyled": "/api/symbols/sparkles.core_cli.styled_template.writestyled.writestyled",
    "sparkles.core_cli.term_size.Handler": "/api/symbols/sparkles.core_cli.term_size.handler",
    "sparkles.core_cli.term_size.setTermWindowSizeHandler": "/api/symbols/sparkles.core_cli.term_size.settermwindowsizehandler",
    "sparkles.core_cli.term_size.SIGWINCH": "/api/symbols/sparkles.core_cli.term_size.sigwinch",
    "sparkles.core_cli.term_style.escapeSeq": "/api/symbols/sparkles.core_cli.term_style.escapeseq",
    "sparkles.core_cli.term_style.numToString": "/api/symbols/sparkles.core_cli.term_style.numtostring",
    "sparkles.core_cli.term_style.numToString.numToString": "/api/symbols/sparkles.core_cli.term_style.numtostring.numtostring",
    "sparkles.core_cli.term_style.sizeForUnsignedNumberBuffer": "/api/symbols/sparkles.core_cli.term_style.sizeforunsignednumberbuffer",
    "sparkles.core_cli.term_style.sizeForUnsignedNumberBuffer.sizeForUnsignedNumberBuffer": "/api/symbols/sparkles.core_cli.term_style.sizeforunsignednumberbuffer.sizeforunsignednumberbuffer",
    "sparkles.core_cli.term_style.Style": "/api/symbols/sparkles.core_cli.term_style.style",
    "sparkles.core_cli.term_style.Style.bgBlack": "/api/symbols/sparkles.core_cli.term_style.style.bgblack",
    "sparkles.core_cli.term_style.Style.bgBlue": "/api/symbols/sparkles.core_cli.term_style.style.bgblue",
    "sparkles.core_cli.term_style.Style.bgBrightBlue": "/api/symbols/sparkles.core_cli.term_style.style.bgbrightblue",
    "sparkles.core_cli.term_style.Style.bgBrightCyan": "/api/symbols/sparkles.core_cli.term_style.style.bgbrightcyan",
    "sparkles.core_cli.term_style.Style.bgBrightGreen": "/api/symbols/sparkles.core_cli.term_style.style.bgbrightgreen",
    "sparkles.core_cli.term_style.Style.bgBrightMagenta": "/api/symbols/sparkles.core_cli.term_style.style.bgbrightmagenta",
    "sparkles.core_cli.term_style.Style.bgBrightRed": "/api/symbols/sparkles.core_cli.term_style.style.bgbrightred",
    "sparkles.core_cli.term_style.Style.bgBrightWhite": "/api/symbols/sparkles.core_cli.term_style.style.bgbrightwhite",
    "sparkles.core_cli.term_style.Style.bgBrightYellow": "/api/symbols/sparkles.core_cli.term_style.style.bgbrightyellow",
    "sparkles.core_cli.term_style.Style.bgCyan": "/api/symbols/sparkles.core_cli.term_style.style.bgcyan",
    "sparkles.core_cli.term_style.Style.bgGray": "/api/symbols/sparkles.core_cli.term_style.style.bggray",
    "sparkles.core_cli.term_style.Style.bgGreen": "/api/symbols/sparkles.core_cli.term_style.style.bggreen",
    "sparkles.core_cli.term_style.Style.bgMagenta": "/api/symbols/sparkles.core_cli.term_style.style.bgmagenta",
    "sparkles.core_cli.term_style.Style.bgRed": "/api/symbols/sparkles.core_cli.term_style.style.bgred",
    "sparkles.core_cli.term_style.Style.bgWhite": "/api/symbols/sparkles.core_cli.term_style.style.bgwhite",
    "sparkles.core_cli.term_style.Style.bgYellow": "/api/symbols/sparkles.core_cli.term_style.style.bgyellow",
    "sparkles.core_cli.term_style.Style.black": "/api/symbols/sparkles.core_cli.term_style.style.black",
    "sparkles.core_cli.term_style.Style.blue": "/api/symbols/sparkles.core_cli.term_style.style.blue",
    "sparkles.core_cli.term_style.Style.bold": "/api/symbols/sparkles.core_cli.term_style.style.bold",
    "sparkles.core_cli.term_style.Style.brightBlue": "/api/symbols/sparkles.core_cli.term_style.style.brightblue",
    "sparkles.core_cli.term_style.Style.brightCyan": "/api/symbols/sparkles.core_cli.term_style.style.brightcyan",
    "sparkles.core_cli.term_style.Style.brightGreen": "/api/symbols/sparkles.core_cli.term_style.style.brightgreen",
    "sparkles.core_cli.term_style.Style.brightMagenta": "/api/symbols/sparkles.core_cli.term_style.style.brightmagenta",
    "sparkles.core_cli.term_style.Style.brightRed": "/api/symbols/sparkles.core_cli.term_style.style.brightred",
    "sparkles.core_cli.term_style.Style.brightWhite": "/api/symbols/sparkles.core_cli.term_style.style.brightwhite",
    "sparkles.core_cli.term_style.Style.brightYellow": "/api/symbols/sparkles.core_cli.term_style.style.brightyellow",
    "sparkles.core_cli.term_style.Style.cyan": "/api/symbols/sparkles.core_cli.term_style.style.cyan",
    "sparkles.core_cli.term_style.Style.dim": "/api/symbols/sparkles.core_cli.term_style.style.dim",
    "sparkles.core_cli.term_style.Style.gray": "/api/symbols/sparkles.core_cli.term_style.style.gray",
    "sparkles.core_cli.term_style.Style.green": "/api/symbols/sparkles.core_cli.term_style.style.green",
    "sparkles.core_cli.term_style.Style.hidden": "/api/symbols/sparkles.core_cli.term_style.style.hidden",
    "sparkles.core_cli.term_style.Style.inverse": "/api/symbols/sparkles.core_cli.term_style.style.inverse",
    "sparkles.core_cli.term_style.Style.italic": "/api/symbols/sparkles.core_cli.term_style.style.italic",
    "sparkles.core_cli.term_style.Style.magenta": "/api/symbols/sparkles.core_cli.term_style.style.magenta",
    "sparkles.core_cli.term_style.Style.none": "/api/symbols/sparkles.core_cli.term_style.style.none",
    "sparkles.core_cli.term_style.Style.red": "/api/symbols/sparkles.core_cli.term_style.style.red",
    "sparkles.core_cli.term_style.Style.reset": "/api/symbols/sparkles.core_cli.term_style.style.reset",
    "sparkles.core_cli.term_style.Style.strikethrough": "/api/symbols/sparkles.core_cli.term_style.style.strikethrough",
    "sparkles.core_cli.term_style.Style.underline": "/api/symbols/sparkles.core_cli.term_style.style.underline",
    "sparkles.core_cli.term_style.Style.white": "/api/symbols/sparkles.core_cli.term_style.style.white",
    "sparkles.core_cli.term_style.Style.yellow": "/api/symbols/sparkles.core_cli.term_style.style.yellow",
    "sparkles.core_cli.term_style.styleName": "/api/symbols/sparkles.core_cli.term_style.stylename",
    "sparkles.core_cli.term_style.styleSample": "/api/symbols/sparkles.core_cli.term_style.stylesample",
    "sparkles.core_cli.term_style.stylize": "/api/symbols/sparkles.core_cli.term_style.stylize",
    "sparkles.core_cli.term_style.stylizedTextBuilder": "/api/symbols/sparkles.core_cli.term_style.stylizedtextbuilder",
    "sparkles.core_cli.term_unstyle.unstyle": "/api/symbols/sparkles.core_cli.term_unstyle.unstyle",
    "sparkles.core_cli.term_unstyle.unstyle.unstyle": "/api/symbols/sparkles.core_cli.term_unstyle.unstyle.unstyle",
    "sparkles.core_cli.term_unstyle.unstyledLength": "/api/symbols/sparkles.core_cli.term_unstyle.unstyledlength",
    "sparkles.core_cli.term_unstyle.unstyledLength.unstyledLength": "/api/symbols/sparkles.core_cli.term_unstyle.unstyledlength.unstyledlength",
    "sparkles.core_cli.text_writers.writeEscapedChar": "/api/symbols/sparkles.core_cli.text_writers.writeescapedchar",
    "sparkles.core_cli.text_writers.writeEscapedChar.writeEscapedChar": "/api/symbols/sparkles.core_cli.text_writers.writeescapedchar.writeescapedchar",
    "sparkles.core_cli.text_writers.writeEscapedCharLiteral": "/api/symbols/sparkles.core_cli.text_writers.writeescapedcharliteral",
    "sparkles.core_cli.text_writers.writeEscapedCharLiteral.writeEscapedCharLiteral": "/api/symbols/sparkles.core_cli.text_writers.writeescapedcharliteral.writeescapedcharliteral",
    "sparkles.core_cli.text_writers.writeEscapedString": "/api/symbols/sparkles.core_cli.text_writers.writeescapedstring",
    "sparkles.core_cli.text_writers.writeEscapedString.writeEscapedString": "/api/symbols/sparkles.core_cli.text_writers.writeescapedstring.writeescapedstring",
    "sparkles.core_cli.text_writers.writeEscapeSeq": "/api/symbols/sparkles.core_cli.text_writers.writeescapeseq",
    "sparkles.core_cli.text_writers.writeEscapeSeq.writeEscapeSeq": "/api/symbols/sparkles.core_cli.text_writers.writeescapeseq.writeescapeseq",
    "sparkles.core_cli.text_writers.writeFloat": "/api/symbols/sparkles.core_cli.text_writers.writefloat",
    "sparkles.core_cli.text_writers.writeFloat.writeFloat": "/api/symbols/sparkles.core_cli.text_writers.writefloat.writefloat",
    "sparkles.core_cli.text_writers.writeInteger": "/api/symbols/sparkles.core_cli.text_writers.writeinteger",
    "sparkles.core_cli.text_writers.writeInteger.writeInteger": "/api/symbols/sparkles.core_cli.text_writers.writeinteger.writeinteger",
    "sparkles.core_cli.text_writers.writeStylized": "/api/symbols/sparkles.core_cli.text_writers.writestylized",
    "sparkles.core_cli.text_writers.writeStylized.writeStylized": "/api/symbols/sparkles.core_cli.text_writers.writestylized.writestylized",
    "sparkles.core_cli.ui.box.BoxProps": "/api/symbols/sparkles.core_cli.ui.box.boxprops",
    "sparkles.core_cli.ui.box.BoxProps.bottomLeft": "/api/symbols/sparkles.core_cli.ui.box.boxprops.bottomleft",
    "sparkles.core_cli.ui.box.BoxProps.bottomRight": "/api/symbols/sparkles.core_cli.ui.box.boxprops.bottomright",
    "sparkles.core_cli.ui.box.BoxProps.footer": "/api/symbols/sparkles.core_cli.ui.box.boxprops.footer",
    "sparkles.core_cli.ui.box.BoxProps.horizontalLine": "/api/symbols/sparkles.core_cli.ui.box.boxprops.horizontalline",
    "sparkles.core_cli.ui.box.BoxProps.omitLeftBorder": "/api/symbols/sparkles.core_cli.ui.box.boxprops.omitleftborder",
    "sparkles.core_cli.ui.box.BoxProps.titlePrefix": "/api/symbols/sparkles.core_cli.ui.box.boxprops.titleprefix",
    "sparkles.core_cli.ui.box.BoxProps.titleSuffix": "/api/symbols/sparkles.core_cli.ui.box.boxprops.titlesuffix",
    "sparkles.core_cli.ui.box.BoxProps.topLeft": "/api/symbols/sparkles.core_cli.ui.box.boxprops.topleft",
    "sparkles.core_cli.ui.box.BoxProps.topRight": "/api/symbols/sparkles.core_cli.ui.box.boxprops.topright",
    "sparkles.core_cli.ui.box.BoxProps.verticalLine": "/api/symbols/sparkles.core_cli.ui.box.boxprops.verticalline",
    "sparkles.core_cli.ui.box.drawBox": "/api/symbols/sparkles.core_cli.ui.box.drawbox",
    "sparkles.core_cli.ui.demo.DemoProps": "/api/symbols/sparkles.core_cli.ui.demo.demoprops",
    "sparkles.core_cli.ui.demo.DemoProps.endTitle": "/api/symbols/sparkles.core_cli.ui.demo.demoprops.endtitle",
    "sparkles.core_cli.ui.demo.DemoProps.width": "/api/symbols/sparkles.core_cli.ui.demo.demoprops.width",
    "sparkles.core_cli.ui.demo.runDemo": "/api/symbols/sparkles.core_cli.ui.demo.rundemo",
    "sparkles.core_cli.ui.demo.Section": "/api/symbols/sparkles.core_cli.ui.demo.section",
    "sparkles.core_cli.ui.demo.Section.content": "/api/symbols/sparkles.core_cli.ui.demo.section.content",
    "sparkles.core_cli.ui.demo.Section.header": "/api/symbols/sparkles.core_cli.ui.demo.section.header",
    "sparkles.core_cli.ui.header.drawHeader": "/api/symbols/sparkles.core_cli.ui.header.drawheader",
    "sparkles.core_cli.ui.header.HeaderProps": "/api/symbols/sparkles.core_cli.ui.header.headerprops",
    "sparkles.core_cli.ui.header.HeaderProps.bannerLineChar": "/api/symbols/sparkles.core_cli.ui.header.headerprops.bannerlinechar",
    "sparkles.core_cli.ui.header.HeaderProps.lineChar": "/api/symbols/sparkles.core_cli.ui.header.headerprops.linechar",
    "sparkles.core_cli.ui.header.HeaderProps.style": "/api/symbols/sparkles.core_cli.ui.header.headerprops.style",
    "sparkles.core_cli.ui.header.HeaderProps.titlePadding": "/api/symbols/sparkles.core_cli.ui.header.headerprops.titlepadding",
    "sparkles.core_cli.ui.header.HeaderProps.width": "/api/symbols/sparkles.core_cli.ui.header.headerprops.width",
    "sparkles.core_cli.ui.header.HeaderStyle": "/api/symbols/sparkles.core_cli.ui.header.headerstyle",
    "sparkles.core_cli.ui.header.HeaderStyle.banner": "/api/symbols/sparkles.core_cli.ui.header.headerstyle.banner",
    "sparkles.core_cli.ui.header.HeaderStyle.divider": "/api/symbols/sparkles.core_cli.ui.header.headerstyle.divider",
    "sparkles.core_cli.ui.osc_link.oscLink": "/api/symbols/sparkles.core_cli.ui.osc_link.osclink",
    "sparkles.core_cli.ui.osc_link.oscLinkCloseSeq": "/api/symbols/sparkles.core_cli.ui.osc_link.osclinkcloseseq",
    "sparkles.core_cli.ui.osc_link.oscLinkOpenSeq": "/api/symbols/sparkles.core_cli.ui.osc_link.osclinkopenseq",
    "sparkles.core_cli.ui.osc_link.OscLinkProps": "/api/symbols/sparkles.core_cli.ui.osc_link.osclinkprops",
    "sparkles.core_cli.ui.osc_link.OscLinkProps.id": "/api/symbols/sparkles.core_cli.ui.osc_link.osclinkprops.id",
    "sparkles.core_cli.ui.osc_link.OscLinkProps.terminator": "/api/symbols/sparkles.core_cli.ui.osc_link.osclinkprops.terminator",
    "sparkles.core_cli.ui.osc_link.OscTerminator": "/api/symbols/sparkles.core_cli.ui.osc_link.oscterminator",
    "sparkles.core_cli.ui.osc_link.OscTerminator.bel": "/api/symbols/sparkles.core_cli.ui.osc_link.oscterminator.bel",
    "sparkles.core_cli.ui.osc_link.OscTerminator.st": "/api/symbols/sparkles.core_cli.ui.osc_link.oscterminator.st",
    "sparkles.core_cli.ui.table.columnWidths": "/api/symbols/sparkles.core_cli.ui.table.columnwidths",
    "sparkles.core_cli.ui.table.drawTable": "/api/symbols/sparkles.core_cli.ui.table.drawtable",
    "sparkles.core_cli.ui.table.hasRectangularShape": "/api/symbols/sparkles.core_cli.ui.table.hasrectangularshape",
    "sparkles.core_cli.ui.table.hasRectangularShape.hasRectangularShape": "/api/symbols/sparkles.core_cli.ui.table.hasrectangularshape.hasrectangularshape"
  }
}
